mgab_panda-0.1.dist-info/DESCRIPTION.rst
mgab_panda-0.1.dist-info/METADATA
mgab_panda-0.1.dist-info/RECORD
mgab_panda-0.1.dist-info/WHEEL
mgab_panda-0.1.dist-info/metadata.json
mgab_panda-0.1.dist-info/top_level.txt
panda/__init__.py
panda/__main__.py
