Metadata-Version: 2.0
Name: mgab-panda
Version: 0.1
Summary: The panda song
Home-page: UNKNOWN
Author: mgab
Author-email: mgab@panda.com
License: UNKNOWN
Platform: UNKNOWN
